grscheller/fp/__init__.py
grscheller/fp/err_handling.py
grscheller/fp/function.py
grscheller/fp/iterables.py
grscheller/fp/lazy.py
grscheller/fp/py.typed
grscheller/fp/singletons.py
grscheller/fp/state.py
grscheller_fp-1.2.0.dist-info/LICENSE
grscheller_fp-1.2.0.dist-info/WHEEL
grscheller_fp-1.2.0.dist-info/METADATA
grscheller_fp-1.2.0.dist-info/RECORD
