Metadata-Version: 2.3
Name: grscheller.fp
Version: 1.2.0
Summary: ### Package grscheller.fp - Pythonic Functional Programming
Keywords: functional,functional programming,fp,monad,iterators,maybe,either,lazy,non-strict
Author-email: "Geoffrey R. Scheller" <geoffrey@scheller.com>
Requires-Python: >=3.12
Classifier: Development Status :: 5 - Production/Stable
Classifier: Framework :: Pytest
Classifier: Intended Audience :: Developers
Classifier: License :: OSI Approved :: Apache Software License
Classifier: Operating System :: OS Independent
Classifier: Programming Language :: Python :: 3.13
Classifier: Typing :: Typed
Requires-Dist: pytest >=8.3 ; extra == "test"
Requires-Dist: grscheller.circular-array >=3.8.1, < 3.9 ; extra == "test"
Requires-Dist: grscheller.datastructures >=0.24.0, < 0.25 ; extra == "test"
Project-URL: Changelog, https://github.com/grscheller/fp/blob/main/CHANGELOG.md
Project-URL: Documentation, https://grscheller.github.io/grscheller-pypi-namespace-docs/fp
Project-URL: Source, https://github.com/grscheller/fp
Provides-Extra: test
